opencloning/__init__.py
opencloning/_version.py
opencloning/api_config_utils.py
opencloning/app_settings.py
opencloning/batch_cloning/__init__.py
opencloning/batch_cloning/index.html
opencloning/batch_cloning/pombe/__init__.py
opencloning/batch_cloning/pombe/index.html
opencloning/batch_cloning/pombe/pombe_clone.py
opencloning/batch_cloning/pombe/pombe_gather.py
opencloning/batch_cloning/pombe/pombe_get_primers.py
opencloning/batch_cloning/pombe/pombe_summary.py
opencloning/batch_cloning/ziqiang_et_al2024/__init__.py
opencloning/batch_cloning/ziqiang_et_al2024/index.html
opencloning/batch_cloning/ziqiang_et_al2024/ziqiang_et_al2024.json
opencloning/bug_fixing/README.md
opencloning/bug_fixing/__init__.py
opencloning/bug_fixing/backend_v0_3.py
opencloning/catalogs/__init__.py
opencloning/catalogs/igem2024.yaml
opencloning/catalogs/openDNA_collections.yaml
opencloning/catalogs/readme.txt
opencloning/catalogs/seva.tsv
opencloning/catalogs/snapgene.yaml
opencloning/dna_functions.py
opencloning/dna_utils.py
opencloning/ebic/__init__.py
opencloning/ebic/primer_design.py
opencloning/ebic/primer_design_settings.py
opencloning/endpoints/annotation.py
opencloning/endpoints/assembly.py
opencloning/endpoints/endpoint_utils.py
opencloning/endpoints/external_import.py
opencloning/endpoints/no_assembly.py
opencloning/endpoints/no_input.py
opencloning/endpoints/other.py
opencloning/endpoints/primer_design.py
opencloning/get_router.py
opencloning/http_client.py
opencloning/main.py
opencloning/ncbi_requests.py
opencloning/primer3_functions.py
opencloning/primer_design.py
opencloning/pydantic_models.py
opencloning/request_examples.py
opencloning/temp_functions.py
opencloning/utils.py
opencloning-0.5.1.dist-info/METADATA
opencloning-0.5.1.dist-info/WHEEL
opencloning-0.5.1.dist-info/licenses/LICENSE
opencloning-0.5.1.dist-info/RECORD
