Metadata-Version: 2.4
Name: opencloning
Version: 0.5.1
Summary: Backend of OpenCloning, a web application to generate molecular cloning strategies in json format, and share them with others.
License: MIT
License-File: LICENSE
Author: Manuel Lera-Ramirez
Author-email: manulera14@gmail.com
Requires-Python: >=3.11,<4.0
Classifier: License :: OSI Approved :: MIT License
Classifier: Programming Language :: Python :: 3
Classifier: Programming Language :: Python :: 3.11
Classifier: Programming Language :: Python :: 3.12
Classifier: Programming Language :: Python :: 3.13
Classifier: Programming Language :: Python :: 3.14
Requires-Dist: beautifulsoup4 (>=4.11.1,<5.0.0)
Requires-Dist: biopython (>=1.85,<2.0)
Requires-Dist: fastapi
Requires-Dist: httpx (>=0.28.1,<0.29.0)
Requires-Dist: openpyxl (>=3.1.5,<4.0.0)
Requires-Dist: packaging (>=25.0,<26.0)
Requires-Dist: pairwise-alignments-to-msa (>=0.1.1,<0.2.0)
Requires-Dist: pandas (>=2.2.3,<3.0.0)
Requires-Dist: primer3-py (>=2.3,<3.0)
Requires-Dist: pydantic (>=2.7.1,<3.0.0)
Requires-Dist: pydna (>=5.5.6,<6.0.0)
Requires-Dist: python-multipart
Requires-Dist: pyyaml (>=6.0.2,<7.0.0)
Requires-Dist: regex (>=2024.11.6,<2025.0.0)
Requires-Dist: uvicorn
Project-URL: Repository, https://github.com/manulera/OpenCloning_backend
